mrccleaner
